CHANGES.txt
MANIFEST.in
README.rst
requirements.txt
setup.cfg
setup.py
recipe/__init__.py
recipe.makedocs.egg-info/PKG-INFO
recipe.makedocs.egg-info/SOURCES.txt
recipe.makedocs.egg-info/dependency_links.txt
recipe.makedocs.egg-info/entry_points.txt
recipe.makedocs.egg-info/namespace_packages.txt
recipe.makedocs.egg-info/not-zip-safe
recipe.makedocs.egg-info/requires.txt
recipe.makedocs.egg-info/top_level.txt
recipe/makedocs/__init__.py
recipe/makedocs/tests/__init__.py