Metadata-Version: 1.1
Name: recipe.makedocs
Version: 0.1.3
Summary: zc.buildout recipe to generate and build Sphinx-based documentation in the buildout
Home-page: UNKNOWN
Author: UNKNOWN
Author-email: UNKNOWN
License: UNKNOWN
Platform: UNKNOWN
Classifier: Framework :: Buildout
Classifier: Intended Audience :: Developers
Classifier: Programming Language :: Python :: 2
Classifier: Topic :: Software Development :: Build Tools
Classifier: Topic :: Software Development :: Libraries :: Python Modules
